investimento/__init__.py
investimento/investimentos.py
meu_investimento_ackeley-0.1.dist-info/LICENSE
meu_investimento_ackeley-0.1.dist-info/METADATA
meu_investimento_ackeley-0.1.dist-info/WHEEL
meu_investimento_ackeley-0.1.dist-info/top_level.txt
meu_investimento_ackeley-0.1.dist-info/RECORD
