Metadata-Version: 2.1
Name: meu-investimento-ackeley
Version: 0.1
Summary: Uma biblioteca para cálculos de investimentos.
Home-page: https://github.com/ackeley/fiap
Author: Ackeley Lennon
Author-email: ackeley@hotmail.com
Classifier: Programming Language :: Python :: 3
Classifier: License :: OSI Approved :: MIT License
Classifier: Operating System :: OS Independent
Requires-Python: >=3.11.5
License-File: LICENSE
